{
  "name": "clock_gated_idle",
  "description": "Always-on CPU domain with aggressive RTL clock gating during idle.",
  "upf_version": "2.1",
  "top": "mobile_cpu_top",
  "notes": [
    "UPF still has one always-on domain because this scheme targets dynamic power through clock enables.",
    "The clock-gating controls are core_clk_en and mem_clk_en in u_power_controller."
  ],
  "methodology": {
    "implemented_rtl_features": [
      "u_power_controller generates core_clk_en and mem_clk_en.",
      "u_core_clk_gate gates the CPU-side clock in IDLE and LIGHT_SLEEP.",
      "u_mem_clk_gate gates the memory-side clock in IDLE and LIGHT_SLEEP.",
      "The LSU single-outstanding state machine stalls the front end while a request or response is outstanding.",
      "Fetch/decode/execute observability exposes valid, stall, and clock-enable cycles for check-in metrics."
    ],
    "estimated_features": [
      "Reduced dynamic activity during idle power states.",
      "Reduced dynamic activity during WFI-driven idle residency.",
      "Per-block dynamic savings inferred from activity counts and IEEE 2416 event models."
    ],
    "not_yet_implemented": [
      "Independent dataflow MAC datapath clock gate inside dataflow_unit.",
      "Separate dataflow power domain.",
      "Explicit stall reason counters in RTL.",
      "Instruction ROM read-enable gating separate from PC hold."
    ],
    "detected_opportunities": [
      "front_end_active_during_stall_ratio flags fetch/decode/execute activity during LSU wait states.",
      "dataflow_utilization flags low MAC active cycles relative to clocked idle cycles.",
      "mmio_transactions_per_mac flags unamortized dataflow offload control traffic."
    ],
    "gated_in_rtl": [
      "u_power_controller drives core_clk_en and mem_clk_en.",
      "u_core_clk_gate gates the CPU-side clock when the controller enters IDLE or LIGHT_SLEEP.",
      "u_mem_clk_gate gates the memory-side clock when the controller enters IDLE or LIGHT_SLEEP.",
      "The fetch PC is held during LSU stalls so load/store wait states do not repeatedly advance the front end."
    ],
    "estimated_behavior": [
      "Clock-gating savings are estimated with clock_gating_efficiency and activity_by_power_state.",
      "No CPU or memory power switches are modeled for this scheme; domains remain always-on.",
      "Retention, isolation, and switched-supply energy are not claimed as implemented behavior for this scheme."
    ],
    "designer_use": [
      "Use this scheme to study dynamic-power reduction from idle and stall clock gating before introducing switched domains.",
      "Compare against dvfs_retention_domains when deciding whether leakage/recovery overhead justifies power gating."
    ]
  },
  "domains": [
    {
      "name": "PD_TOP",
      "elements": ["."],
      "include_scope": true,
      "supply": "VDD_TOP",
      "ground": "VSS",
      "always_on": true,
      "states": [
        {"name": "ON", "kind": "FULL_ON", "voltage": 0.80}
      ]
    }
  ],
  "power_states": [
    {"name": "RUN", "domain_states": {"PD_TOP": "ON"}},
    {"name": "IDLE", "domain_states": {"PD_TOP": "ON"}}
  ],
  "estimation": {
    "frequency_mhz": 900,
    "clock_gating_efficiency": 0.48,
    "state_mix": {"RUN": 0.45, "IDLE": 0.55},
    "activity_by_power_state": {"RUN": 1.0, "IDLE": 0.18},
    "retention_overhead_mw": 0.0
  }
}
